{
  "type": "manager",
  "buildingAccess":[{
    "floor":"L4",
    "zone":["A","B","C","D"]
  },
  {
    "floor":"L5",
    "zone":["A","B","C","D"]
  }],
  "team": {
    "name": "iCredit",
    "strength": 10,
    "quota": 6,
    "members":[
      {"name":"Rohit", "code":"M100101", "email": "xyz@cs.com", "team":"iCredit"},
      {"name":"Chanchal", "code":"M100102", "email": "xyz@cs.com", "team":"iCredit"},
      {"name":"Shashi", "code":"M100103", "email": "xyz@cs.com", "team":"iCredit"},
      {"name":"Setia", "code":"M100104", "email": "xyz@cs.com", "team":"iCredit"},
      {"name":"Vaishanvi", "code":"M100105", "email": "xyz@cs.com", "team":"iCredit"},
      {"name":"Praveen", "code":"M100106", "email": "xyz@cs.com", "team":"iCredit"},
      {"name":"Srinidhi", "code":"M100107", "email": "xyz@cs.com", "team":"iCredit"},
      {"name":"Kushal", "code":"M100108", "email": "xyz@cs.com", "team":"iCredit"},
      {"name":"Malini", "code":"M100109", "email": "xyz@cs.com", "team":"iCredit"},
      {"name":"Sai", "code":"M100110",  "email": "xyz@cs.com", "team":"iCredit"}
    ]
  }
}
